gmac-0.2.0.dist-info/METADATA
gmac-0.2.0.dist-info/WHEEL
gmac-0.2.0.dist-info/licenses/LICENSE
gmac/__init__.py
gmac/core.py
gmac/core.pyi
gmac/gmac.pyd
gmac/io.py
gmac/io.pyi
gmac/morph.py
gmac/morph.pyi
gmac/py.typed
gmac-0.2.0.dist-info/RECORD
