Metadata-Version: 2.4
Name: gmac
Version: 0.2.0
Classifier: Development Status :: 4 - Beta
Classifier: Intended Audience :: Science/Research
Classifier: Intended Audience :: Developers
Classifier: Programming Language :: Rust
Classifier: Programming Language :: Python :: 3
Classifier: Programming Language :: Python :: 3.10
Classifier: Programming Language :: Python :: 3.11
Classifier: Programming Language :: Python :: 3.12
Classifier: Topic :: Scientific/Engineering
Classifier: Topic :: Scientific/Engineering :: Mathematics
Classifier: Topic :: Software Development :: Libraries :: Python Modules
License-File: LICENSE
Summary: A fast geometry manipulation and creation library written in Rust, wrapped in python
Keywords: geometry,3d,mesh,deformation,morphing,computational-geometry,scientific-computing,cad,ffd,rbf,free-form-deformation,radial-basis-function,radial basis function
Author: Aleksander Lovric <alexlovric@gmail.com>
Author-email: Aleksander Lovric <alexlovric@gmail.com>
License: MIT
Requires-Python: >=3.10
Project-URL: Source Code, https://github.com/alexlovric/gmac
